libbson-1.0.0.0.0.dylib
libbson-1.0.0.dylib
libbson-1.0.dylib
pyftdc.cpython-310-darwin.so
bson/README
bson/SConscript
bson/bson_bin_util.h
bson/bson_bm.cpp
bson/bson_comparator_interface_base.cpp
bson/bson_comparator_interface_base.h
bson/bson_depth.cpp
bson/bson_depth.h
bson/bson_duration.h
bson/bson_field.h
bson/bson_field_test.cpp
bson/bson_obj_data_type_test.cpp
bson/bson_obj_test.cpp
bson/bson_time_support.h
bson/bson_validate.cpp
bson/bson_validate.h
bson/bson_validate_fuzzer.cpp
bson/bson_validate_old.cpp
bson/bson_validate_old.h
bson/bson_validate_test.cpp
bson/bsonelement.cpp
bson/bsonelement.h
bson/bsonelement_comparator.h
bson/bsonelement_comparator_interface.h
bson/bsonelement_test.cpp
bson/bsonelementvalue.cpp
bson/bsonelementvalue.h
bson/bsonmisc.cpp
bson/bsonmisc.h
bson/bsonobj.cpp
bson/bsonobj.h
bson/bsonobj_comparator.h
bson/bsonobj_comparator_interface.h
bson/bsonobjbuilder.cpp
bson/bsonobjbuilder.h
bson/bsonobjbuilder_test.cpp
bson/bsontypes.cpp
bson/bsontypes.h
bson/bsontypes_util.h
bson/generator_extended_canonical_2_0_0.h
bson/generator_extended_relaxed_2_0_0.h
bson/generator_legacy_strict.h
bson/json.cpp
bson/json.h
bson/oid.cpp
bson/oid.h
bson/oid_test.cpp
bson/ordering.h
bson/simple_bsonelement_comparator.cpp
bson/simple_bsonelement_comparator.h
bson/simple_bsonobj_comparator.cpp
bson/simple_bsonobj_comparator.h
bson/simple_bsonobj_comparator_test.cpp
bson/timestamp.cpp
bson/timestamp.h
bson/ugly_bson_integration_test.cpp
bson/unordered_fields_bsonelement_comparator.h
bson/unordered_fields_bsonobj_comparator.h
bson/mutable/SConscript
bson/mutable/algorithm.h
bson/mutable/api.h
bson/mutable/const_element-inl.h
bson/mutable/const_element.h
bson/mutable/damage_vector.h
bson/mutable/document.cpp
bson/mutable/document.h
bson/mutable/element.cpp
bson/mutable/element.h
bson/mutable/mutable_bson_algo_test.cpp
bson/mutable/mutable_bson_test.cpp
bson/mutable/mutable_bson_test_utils.cpp
bson/mutable/mutable_bson_test_utils.h
bson/util/SConscript
pyftdc-0.3.11.dist-info/LICENSE
pyftdc-0.3.11.dist-info/METADATA
pyftdc-0.3.11.dist-info/WHEEL
pyftdc-0.3.11.dist-info/top_level.txt
pyftdc-0.3.11.dist-info/RECORD
