Metadata-Version: 2.1
Name: pyftdc
Version: 0.3.11
Summary: A parser for MongoDB FTDC files, with Python bindings.
Author: Jorge Imperial
Author-email: Jorge Imperial <jlimperial@protonmail.com>
Project-URL: Homepage, https://gitlab.com/jimper/mongo_ftdc
Project-URL: Bug Tracker, https://gitlab.com/jimper/issues
Classifier: Programming Language :: Python :: 3
Classifier: License :: OSI Approved :: MIT License
Classifier: Operating System :: OS Independent
Requires-Python: >=3.8
License-File: LICENSE
